{
  "kind": "singleType",
  "collectionName": "settings",
  "info": {
    "singularName": "setting",
    "pluralName": "settings",
    "displayName": "Setting"
  },
  "options": {
    "draftAndPublish": true
  },
  "pluginOptions": {
    "i18n": {
      "localized": true
    }
  },
  "attributes": {
    "siteName": {
      "type": "string",
      "pluginOptions": {
        "i18n": {
          "localized": false
        }
      },
      "required": true
    },
    "siteLogo": {
      "type": "media",
      "pluginOptions": {
        "i18n": {
          "localized": false
        }
      },
      "multiple": false,
      "required": false,
      "allowedTypes": [
        "images",
        "files"
      ]
    },
    "favicon": {
      "type": "media",
      "pluginOptions": {
        "i18n": {
          "localized": false
        }
      },
      "multiple": false,
      "allowedTypes": [
        "images",
        "files"
      ]
    },
    "defaultSeoTitleTemplate": {
      "type": "string",
      "pluginOptions": {
        "i18n": {
          "localized": true
        }
      }
    },
    "contactEmail": {
      "type": "email",
      "pluginOptions": {
        "i18n": {
          "localized": false
        }
      }
    },
    "footerCopyright": {
      "type": "string",
      "pluginOptions": {
        "i18n": {
          "localized": true
        }
      }
    },
    "aboutPage": {
      "type": "customField",
      "pluginOptions": {
        "i18n": {
          "localized": true
        }
      },
      "customField": "plugin::ckeditor5.CKEditor",
      "options": {
        "preset": "defaultMarkdown"
      }
    },
    "websiteMetadata": {
      "type": "json",
      "pluginOptions": {
        "i18n": {
          "localized": true
        }
      }
    }
  }
}
